lynxius/__init__.py
lynxius/client.py
lynxius/datasets/__init__.py
lynxius/datasets/types.py
lynxius/evals/__init__.py
lynxius/evals/answer_correctness.py
lynxius/evals/bert_score.py
lynxius/evals/context_precision.py
lynxius/evals/custom_eval.py
lynxius/evals/evaluator.py
lynxius/evals/json_diff.py
lynxius/evals/semantic_similarity.py
lynxius/rag/__init__.py
lynxius/rag/types.py
lynxius_evals/__init__.py
lynxius_evals/evaluators/__init__.py
lynxius_evals/evaluators/answer_correctness_eval.py
lynxius_evals/evaluators/bert_score_eval.py
lynxius_evals/evaluators/context_precision_eval.py
lynxius_evals/evaluators/json_diff_evaluator.py
lynxius_evals/evaluators/llm_based_eval.py
lynxius_evals/evaluators/semantic_similarity_eval.py
lynxius_evals/models/__init__.py
lynxius_evals/models/eval_model.py
lynxius_evals/models/openai.py
lynxius_evals/prompts/__init__.py
lynxius_evals/prompts/answer_correctness_prompt.py
lynxius_evals/prompts/context_precision_prompt.py
lynxius_evals/prompts/eval_prompt.py
lynxius-1.2.0.dist-info/LICENSE
lynxius-1.2.0.dist-info/METADATA
lynxius-1.2.0.dist-info/WHEEL
lynxius-1.2.0.dist-info/entry_points.txt
lynxius-1.2.0.dist-info/top_level.txt
lynxius-1.2.0.dist-info/RECORD
