Metadata-Version: 2.1
Name: lynxius
Version: 1.2.0
Summary: Lynxius speeds up LLM evaluation and prevents errors before they reach users.
Home-page: https://github.com/lynxius/lynxius-python
Author: Lynxius Inc.
Author-email: contact@lynxius.ai
Keywords: lynxius
Classifier: Development Status :: 5 - Production/Stable
Classifier: Intended Audience :: Developers
Classifier: License :: OSI Approved :: MIT License
Classifier: Natural Language :: English
Classifier: Operating System :: OS Independent
Classifier: Programming Language :: Python :: 3
Classifier: Programming Language :: Python :: 3.10
Classifier: Programming Language :: Python :: 3.12
Requires-Python: >=3.10
License-File: LICENSE
Requires-Dist: httpx >=0.27.0
Requires-Dist: nltk >=3.8.1
Requires-Dist: numpy >=2.0.0
Requires-Dist: python-Levenshtein >=0.25.1
Requires-Dist: tiktoken >=0.7.0
Requires-Dist: openai >=1.35.1
